goat_adapters/ag2/__init__.py
goat_adapters/ag2/adapter.py
goat_sdk_adapter_ag2-0.1.0.dist-info/METADATA
goat_sdk_adapter_ag2-0.1.0.dist-info/WHEEL
goat_sdk_adapter_ag2-0.1.0.dist-info/RECORD
