Metadata-Version: 2.1
Name: goat-sdk-adapter-ag2
Version: 0.1.0
Summary: Goat adapter for AG2
Home-page: https://ohmygoat.dev/
Keywords: goat,sdk,web3,agents,ai
Author: Andrea Villa
Author-email: andreakarimodm@gmail.com
Requires-Python: >=3.10,<3.14
Classifier: Programming Language :: Python :: 3
Classifier: Programming Language :: Python :: 3.10
Classifier: Programming Language :: Python :: 3.11
Classifier: Programming Language :: Python :: 3.12
Requires-Dist: ag2 (>=0.8.0)
Requires-Dist: goat-sdk (>=0.1.6)
Project-URL: Bug Tracker, https://github.com/goat-sdk/goat/issues
Project-URL: Repository, https://github.com/goat-sdk/goat
